{
  "name": "pricingtable",
  "type": "registry:component",
  "dependencies": [
    "react",
    "react-dom",
    "@fragment_ui/ui"
  ],
  "files": [
    {
      "path": "components/ui/PricingTable.tsx",
      "content": "import * as React from \"react\";\nimport { Card, CardHeader, CardTitle, CardDescription, CardContent, CardFooter } from \"@fragment_ui/ui\";\nimport { Button } from \"@fragment_ui/ui\";\nimport { Badge } from \"@fragment_ui/ui\";\nimport clsx from \"clsx\";\n\nexport interface PricingFeature {\n  name: string;\n  included?: boolean;\n  description?: string;\n}\n\nexport interface PricingTier {\n  name: string;\n  description?: string;\n  price: string;\n  pricePeriod?: string;\n  priceDescription?: string;\n  features: PricingFeature[];\n  ctaText: string;\n  ctaOnClick?: () => void;\n  ctaHref?: string;\n  popular?: boolean;\n  disabled?: boolean;\n}\n\nexport interface PricingTableProps {\n  tiers: PricingTier[];\n  className?: string;\n}\n\nexport function PricingTable({ tiers, className }: PricingTableProps) {\n  return (\n    <div className={clsx(\"grid gap-6 md:grid-cols-2 lg:grid-cols-3\", className)}>\n      {tiers.map((tier, index) => (\n        <Card\n          key={index}\n          className={clsx(\n            \"flex flex-col\",\n            tier.popular && \"border-[color:var(--color-brand-primary)] shadow-lg\",\n            tier.disabled && \"opacity-60\"\n          )}\n        >\n          <CardHeader>\n            <div className=\"flex items-center justify-between\">\n              <CardTitle>{tier.name}</CardTitle>\n              {tier.popular && (\n                <Badge variant=\"solid\" size=\"sm\">\n                  Popular\n                </Badge>\n              )}\n            </div>\n            {tier.description && (\n              <CardDescription>{tier.description}</CardDescription>\n            )}\n            <div className=\"mt-4\">\n              <div className=\"flex items-baseline gap-1\">\n                <span className=\"text-4xl font-bold\">{tier.price}</span>\n                {tier.pricePeriod && (\n                  <span className=\"text-sm text-[color:var(--color-fg-muted)]\">\n                    /{tier.pricePeriod}\n                  </span>\n                )}\n              </div>\n              {tier.priceDescription && (\n                <p className=\"mt-1 text-sm text-[color:var(--color-fg-muted)]\">\n                  {tier.priceDescription}\n                </p>\n              )}\n            </div>\n          </CardHeader>\n          <CardContent className=\"flex-1\">\n            <ul className=\"space-y-3\">\n              {tier.features.map((feature, featureIndex) => (\n                <li key={featureIndex} className=\"flex items-start gap-2\">\n                  <span\n                    className={clsx(\n                      \"mt-0.5 flex-shrink-0\",\n                      feature.included !== false\n                        ? \"text-[color:var(--color-brand-primary)]\"\n                        : \"text-[color:var(--color-fg-muted)]\"\n                    )}\n                  >\n                    {feature.included !== false ? \"✓\" : \"✗\"}\n                  </span>\n                  <div className=\"flex-1\">\n                    <span\n                      className={clsx(\n                        feature.included !== false\n                          ? \"text-[color:var(--color-fg-base)]\"\n                          : \"text-[color:var(--color-fg-muted)] line-through\"\n                      )}\n                    >\n                      {feature.name}\n                    </span>\n                    {feature.description && (\n                      <p className=\"mt-0.5 text-xs text-[color:var(--color-fg-muted)]\">\n                        {feature.description}\n                      </p>\n                    )}\n                  </div>\n                </li>\n              ))}\n            </ul>\n          </CardContent>\n          <CardFooter>\n            {tier.ctaHref ? (\n              <a href={tier.ctaHref} className=\"w-full\">\n                <Button\n                  variant=\"solid\"\n                  size=\"lg\"\n                  className=\"w-full\"\n                  disabled={tier.disabled}\n                >\n                  {tier.ctaText}\n                </Button>\n              </a>\n            ) : (\n              <Button\n                variant={tier.popular ? \"solid\" : \"outline\"}\n                size=\"lg\"\n                className=\"w-full\"\n                onClick={tier.ctaOnClick}\n                disabled={tier.disabled}\n              >\n                {tier.ctaText}\n              </Button>\n            )}\n          </CardFooter>\n        </Card>\n      ))}\n    </div>\n  );\n}\n\n"
    }
  ]
}